hello_world_2/project-alu.v

module mini_alu (
    input [31:0] a,
    input [31:0] b, 
    input c1, 
    
    input [3:0] opcode, 
    output reg [31:0] y
    );
    always @(*) begin
        case (opcode)
            4'b0000: y = a + b; // Add
            4'b0001: y = a + b + c1; // Add with carry 
            4'b0010: y = a - b;
            4'b0011: y = a - b - c1;
            4'b0100: y = a && b;
            4'b0101: y = a ^ b;
            4'b0110: y = a xor b;
            4'b0111: y = a xnor b;
            4'b1000: y = a && ~b;
            4'b1001: y = a ^ ~b;
            4'b1010: y = a << b;
            4'b1011: y = a >> b;
            4'b1100: y = a >>> b; 
            4'b1101: y = a;
            4'b1110: y = b;
            4'b1111: y = ~b;
        endcase
    end
endmodule


// Source Operand2 Handler
/*
TODO: Preguntar al profe que rayos se supone que 
haga este modulo que pidio

*/
module source_operand (
    input [31:0] R,
    input [21:0] Imm,
    input reg [3:0] Is,
    output [31:0] N
);

always @(*) begin
    case(Is)
        4'b000: N = Imm || 0b0000000000;
        4'b001: N = Imm || 0b0000000000;
        4'b010: N = Imm || 0b0000000000;
        4'b011: N = Imm || 0b0000000000;
        4'b100: N = Imm[21:0] <= { {8{Is[7]}}, Is[7:0] }; // No tengo idea de lo que hago :v

        4'b1000: N = R;

        4'b1100: N = R;

        4'b1110: N = R;

    endcase
end

endmodule


module register_4bit (
    output reg [3:0] Q,
    input [3:0] D,
    input LE, Clr, Clk
    );
    always @ (posedge Clk)
    if (Clr) Q <= 4’b0000 ;
    else if (LE) Q <= D;
endmodule

src/alu.v

/***************************************************************
* Module: alu
***************************************************************
* Description:
* This module implements an Arithmetic Logic Unit (ALU) that performs various arithmetic and logic operations on two 32-bit inputs (a and b) based on a 4-bit opcode. The ALU computes the result (y) and sets the flags (Z, N, C, V) based on the operation performed.
* 
* Inputs:
* - a [31:0]: 32-bit input A
* - b [31:0]: 32-bit input B
* - cin: Carry-in input
* - opcode [3:0]: 4-bit operation code
* 
* Outputs:
* - y [31:0]: 32-bit output result
* - flags [3:0]: Flags indicating the result status (Z, N, C, V)
* 
* Limitations:
* - The ALU module only supports 32-bit inputs and outputs. Other bit widths are not supported.
* 
* Usage:
* 1. Instantiate the `alu` module in your design and provide the required inputs and outputs.
* 2. Connect the 32-bit inputs `a` and `b` to the desired sources.
* 3. Set the `cin` input to the carry-in value if required.
* 4. Assign the desired operation code to the `opcode` input to select the desired operation.
* 5. The output `y` will hold the result of the operation, and `flags` will indicate the status flags (Z, N, C, V) based on the operation performed.
* 
* Example:
* ```verilog
* module testbench;
*     reg [31:0] a, b;
*     reg cin;
*     reg [3:0] opcode;
*     wire [31:0] y;
*     wire [3:0] flags;
* 
*     alu alu_inst (
*         .a(a),
*         .b(b),
*         .cin(cin),
*         .opcode(opcode),
*         .y(y),
*         .flags(flags)
*     );
* 
*     initial begin
*         // Set input values
*         a = 32'hA5A5A5A5;
*         b = 32'hB5B5B5B5;
*         cin = 1'b1;
*         opcode = 4'b0000; // Addition operation
* 
*         // Wait some time for computation
*         #10;
* 
*         // Check outputs
*         $display("Result: %h", y);
*         $display("Flags: %b", flags);
*     end
* endmodule
* ```
***************************************************************/
module alu (
    input [31:0] a,
    input [31:0] b, 
    input cin, 
    input [3:0] opcode, 
    output reg  [31:0] y,
    output reg [3:0] flags
    );
    
    reg [32:0] carry;

    // reg Z;
    // reg N;
    // reg C;
    // reg V;
    
    /* Explanation:
    * Z -> If Outout was 0 or not
    * N -> Negative
    * C -> Carry
    * V -> Overflow
    */
    always @* begin
        case (opcode)   // Flag order: Z N C V
            4'b0000: begin
                {carry, y} = a + b; // Add => A + B

                // Z = (y == 32'b0) ? 1:0;
                // N = (y[31] == 1'b1) ? 1:0;
                // C = carry[0];
                // V = (~a[31] && ~b[31] && y[31]) | (a[31] && b[31] && ~y[31]);
                // flags = {Z, N, C, V};
                flags = {y == 32'b0, y[31], carry[0], ((~a[31] && ~b[31] && y[31]) | (a[31] && b[31] && ~y[31]))};
            end
            4'b0001: begin
                {carry, y} = a + b + cin; // Add with carry => A + B + cin

                // Z = (y == 32'b0) ? 1:0;
                // N = (y[31] == 1'b1) ? 1:0;
                // C = carry[32];
                // V = (~a[31] && ~b[31] && y[31]) | (a[31] && b[31] && ~y[31]);
                // flags = {Z, N, C, V};
                flags = {y == 32'b0, y[31], carry[0], ((~a[31] && ~b[31] && y[31]) | (a[31] && b[31] && ~y[31]))};
            end
            4'b0010: begin
                {carry, y} = a - b;

                // Z = (y == 32'b0) ? 1:0;
                // N = (y[31] == 1'b1) ? 1:0;
                // C = carry[32];
                // V = ({carry, y[31]} == 2'b01);
                // flags = {Z, N, C, V};  
                flags = {y == 32'b0, y[31] == 1'b1, carry[32], ({carry, y[31]} == 2'b01)};
            end
            4'b0011: begin 
                {carry, y} = a - b - cin;

                // Z = (y == 32'b0) ? 1:0;
                // N = (y[31] == 1'b1) ? 1:0;
                // C = carry[32];
                // V = ({carry, y[31]} == 2'b01);
                // flags = {Z, N, C, V};
                flags = {y == 32'b0, y[31] == 1'b1, carry[32], ({carry, y[31]} == 2'b01)};
            end
            4'b0100: begin
                {carry, y} = a && b;

                // Z = (y == 32'b0) ? 1:0;
                // N = (y[31] == 1'b1) ? 1:0;
                // C = 1'b0;
                // V = 1'b0;
                // flags = {Z, N, C, V};
                flags = {y == 32'b0, y[31] == 1'b1, 1'b0, 1'b0};
            end
            4'b0101: begin
                {carry, y} = a | b;

                // Z = (y == 32'b0) ? 1:0;
                // N = (y[31] == 1'b1) ? 1:0;
                // C = 1'b0;
                // V = 1'b0;
                // flags = {Z, N, C, V};
                flags = {y == 32'b0, y[31] == 1'b1, 1'b0, 1'b0};
            end
            4'b0110: begin
                {carry, y} = a ^ b;

                // Z = (y == 32'b0) ? 1:0;
                // N = (y[31] == 1'b1) ? 1:0;
                // C = 1'b0;
                // V = 1'b0;
                // flags = {Z, N, C, V};
                flags = {y == 32'b0, y[31] == 1'b1, 1'b0, 1'b0};
            end
            4'b0111: begin
                {carry, y} = ~(a ^ b);

                // Z = (y == 32'b0) ? 1:0;
                // N = (y[31] == 1'b1) ? 1:0;
                // C = 1'b0;
                // V = 1'b0;
                // flags = {Z, N, C, V};
            end
            4'b1000: begin
                {carry, y} = a && ~b;

                // Z = (y == 32'b0) ? 1:0;
                // N = (y[31] == 1'b1) ? 1:0;
                // C = 1'b0;
                // V = 1'b0;
                // flags = {Z, N, C, V};
                flags = {y == 32'b0, y[31] == 1'b1, 1'b0, 1'b0};
            end
            4'b1001: begin
                {carry, y} = a ^ ~b;
                
                // Z = (y == 32'b0) ? 1:0;
                // N = (y[31] == 1'b1) ? 1:0;
                // C = 1'b0;
                // V = 1'b0;
                // flags = {Z, N, C, V};
                flags = {y == 32'b0, y[31] == 1'b1, 1'b0, 1'b0};
            end
            4'b1010: {carry, y} = a << b;
            4'b1011: {carry, y} = a >> b;
            4'b1100: {carry, y} = $signed(a) >>> b[4:0];
            4'b1101: {carry, y} = a;
            4'b1110: {carry, y} = b;
            4'b1111: {carry, y} = ~b;
        endcase
    end
endmodule

testers/alu-tester.v
`timescale 1ns / 1ns
`include "src/alu.v"

// uncomment this so you only need to run the
// tester module :D
// `include "project/src/project-alu.v"
// `include "project-alu.v"

module alu_tb;
    reg  [31:0] a;
    reg  [31:0] b;
    reg  cin;
    reg  [3:0] opcode;
    wire [31:0] y;
    wire [3:0] flags;

    alu uut (
    .a(a),
    .b(b),
    .cin(cin),
    .opcode(opcode),
    .y(y),
    .flags(flags)
    );

    initial begin  
        $display("Test 1\n");
        #10
        
        //
        a = 32'b11000000000000000000000000000001;
        b = 32'b00000000000000000000000000000011;

        cin = 1'b1;
        opcode = 4'b0000;
        repeat (15) #20 opcode = opcode + 4'b0001;

        #100
        #3 $display("\nTest 2\n");
        a = 32'b00000000000000000000000000000000;
        b = 32'b00000000000000000000000000000001;
        cin = 1'b0;
        opcode = 4'b0000;
        repeat (15) #20 opcode = opcode + 4'b0001;

        #100
        
        #3 $display("\nTest 3\n");
        a = 32'b01000000000000000000000000000000;
        b = 32'b01000000000000000000000000000000;
        cin = 1'b0;
        opcode = 4'b0000;
        repeat (15) #20 opcode = opcode + 4'b0001;
        
        #100

        #3 $display("\nTest 4\n");
        a = 32'b10000000000000000000000000001000;
        b = 32'b10000000000000000000000001000000;
        cin = 1'b0;
        opcode = 4'b0000;
        repeat (15) #20 opcode = opcode + 4'b0001;

        #100

        #3 $display("\nTest 5\n");

        a = 32'b00000000000000000000000000000001;
        b = 32'b10111111111111111111111111111111;
        cin = 1'b0;
        opcode = 4'b0000;
        repeat (15) #20 opcode = opcode + 4'b0001;

        #100

        #3 $display("\nTest 6\n");

        // shift test
        a = 32'b11000000000000000000000000000001;
        b = 32'b10111111111111111111111111000011;
        cin = 1'b0;
        opcode = 4'b0000;
        repeat (15) #20 opcode = opcode + 4'b0001;
    end
    
    initial begin
        $dumpfile("gtk-wave-testers/alu.vcd"); // pass this to GTK Wave to visualize better wtf is going on
        $dumpvars(0, alu_tb);
        
        #10 $display("| opcode |%17sA%16s|%17sB%16s|%17sY%16s| flag |", "", "", "", "", "", "");
        #10 $display("|--------|%s|%s|%s|------|", "----------------------------------", "----------------------------------", "----------------------------------");
        #15 $monitor("| %b   | %30b | %30b | %30b | %b |", opcode, a, b, y, flags);
    end
endmodule

gtk-wave-testers/alu.vcd
$date
	Fri Jun  2 10:46:49 2023
$end
$version
	Icarus Verilog
$end
$timescale
	1ns
$end
$scope module alu_tb $end
$var wire 32 ! y [31:0] $end
$var wire 4 " flags [3:0] $end
$var reg 32 # a [31:0] $end
$var reg 32 $ b [31:0] $end
$var reg 1 % cin $end
$var reg 4 & opcode [3:0] $end
$scope module uut $end
$var wire 32 ' a [31:0] $end
$var wire 32 ( b [31:0] $end
$var wire 1 % cin $end
$var wire 4 ) opcode [3:0] $end
$var reg 33 * carry [32:0] $end
$var reg 4 + flags [3:0] $end
$var reg 32 , y [31:0] $end
$upscope $end
$upscope $end
$enddefinitions $end
$comment Show the parameter values. $end
$dumpall
$end
#0
$dumpvars
bx ,
bx +
bx *
bx )
bx (
bx '
bx &
x%
bx $
bx #
bx "
bx !
$end
#10
b100 "
b100 +
b0 *
b11000000000000000000000000000100 !
b11000000000000000000000000000100 ,
b0 &
b0 )
1%
b11 $
b11 (
b11000000000000000000000000000001 #
b11000000000000000000000000000001 '
#30
b11000000000000000000000000000101 !
b11000000000000000000000000000101 ,
b1 &
b1 )
#50
b101 "
b101 +
b10111111111111111111111111111110 !
b10111111111111111111111111111110 ,
b10 &
b10 )
#70
b10111111111111111111111111111101 !
b10111111111111111111111111111101 ,
b11 &
b11 )
#90
b0 "
b0 +
b1 !
b1 ,
b100 &
b100 )
#110
b100 "
b100 +
b11000000000000000000000000000011 !
b11000000000000000000000000000011 ,
b101 &
b101 )
#130
b11000000000000000000000000000010 !
b11000000000000000000000000000010 ,
b110 &
b110 )
#150
b111111111111111111111111111111111 *
b111111111111111111111111111101 !
b111111111111111111111111111101 ,
b111 &
b111 )
#170
b0 "
b0 +
b0 *
b1 !
b1 ,
b1000 &
b1000 )
#190
b111111111111111111111111111111111 *
b111111111111111111111111111101 !
b111111111111111111111111111101 ,
b1001 &
b1001 )
#210
b110 *
b1000 !
b1000 ,
b1010 &
b1010 )
#230
b0 *
b11000000000000000000000000000 !
b11000000000000000000000000000 ,
b1011 &
b1011 )
#250
b111111111111111111111111111111111 *
b11111000000000000000000000000000 !
b11111000000000000000000000000000 ,
b1100 &
b1100 )
#270
b0 *
b11000000000000000000000000000001 !
b11000000000000000000000000000001 ,
b1101 &
b1101 )
#290
b11 !
b11 ,
b1110 &
b1110 )
#310
b111111111111111111111111111111111 *
b11111111111111111111111111111100 !
b11111111111111111111111111111100 ,
b1111 &
b1111 )
#413
b0 *
b1 !
b1 ,
b0 &
b0 )
0%
b1 $
b1 (
b0 #
b0 '
#433
b1 &
b1 )
#453
b110 "
b110 +
b111111111111111111111111111111111 *
b11111111111111111111111111111111 !
b11111111111111111111111111111111 ,
b10 &
b10 )
#473
b11 &
b11 )
#493
b1000 "
b1000 +
b0 *
b0 !
b0 ,
b100 &
b100 )
#513
b0 "
b0 +
b1 !
b1 ,
b101 &
b101 )
#533
b110 &
b110 )
#553
b111111111111111111111111111111111 *
b11111111111111111111111111111110 !
b11111111111111111111111111111110 ,
b111 &
b111 )
#573
b1000 "
b1000 +
b0 *
b0 !
b0 ,
b1000 &
b1000 )
#593
b100 "
b100 +
b111111111111111111111111111111111 *
b11111111111111111111111111111110 !
b11111111111111111111111111111110 ,
b1001 &
b1001 )
#613
b0 *
b0 !
b0 ,
b1010 &
b1010 )
#633
b1011 &
b1011 )
#653
b1100 &
b1100 )
#673
b1101 &
b1101 )
#693
b1 !
b1 ,
b1110 &
b1110 )
#713
b111111111111111111111111111111111 *
b11111111111111111111111111111110 !
b11111111111111111111111111111110 ,
b1111 &
b1111 )
#816
b101 "
b101 +
b0 *
b10000000000000000000000000000000 !
b10000000000000000000000000000000 ,
b0 &
b0 )
b1000000000000000000000000000000 $
b1000000000000000000000000000000 (
b1000000000000000000000000000000 #
b1000000000000000000000000000000 '
#836
b1 &
b1 )
#856
b1000 "
b1000 +
b0 !
b0 ,
b10 &
b10 )
#876
b11 &
b11 )
#896
b0 "
b0 +
b1 !
b1 ,
b100 &
b100 )
#916
b1000000000000000000000000000000 !
b1000000000000000000000000000000 ,
b101 &
b101 )
#936
b1000 "
b1000 +
b0 !
b0 ,
b110 &
b110 )
#956
b111111111111111111111111111111111 *
b11111111111111111111111111111111 !
b11111111111111111111111111111111 ,
b111 &
b111 )
#976
b0 "
b0 +
b0 *
b1 !
b1 ,
b1000 &
b1000 )
#996
b100 "
b100 +
b111111111111111111111111111111111 *
b11111111111111111111111111111111 !
b11111111111111111111111111111111 ,
b1001 &
b1001 )
#1016
b0 *
b0 !
b0 ,
b1010 &
b1010 )
#1036
b1011 &
b1011 )
#1056
b1000000000000000000000000000000 !
b1000000000000000000000000000000 ,
b1100 &
b1100 )
#1076
b1101 &
b1101 )
#1096
b1110 &
b1110 )
#1116
b111111111111111111111111111111111 *
b10111111111111111111111111111111 !
b10111111111111111111111111111111 ,
b1111 &
b1111 )
#1219
b11 "
b11 +
b1 *
b1001000 !
b1001000 ,
b0 &
b0 )
b10000000000000000000000001000000 $
b10000000000000000000000001000000 (
b10000000000000000000000000001000 #
b10000000000000000000000000001000 '
#1239
b1 &
b1 )
#1259
b110 "
b110 +
b111111111111111111111111111111111 *
b11111111111111111111111111001000 !
b11111111111111111111111111001000 ,
b10 &
b10 )
#1279
b11 &
b11 )
#1299
b0 "
b0 +
b0 *
b1 !
b1 ,
b100 &
b100 )
#1319
b100 "
b100 +
b10000000000000000000000001001000 !
b10000000000000000000000001001000 ,
b101 &
b101 )
#1339
b0 "
b0 +
b1001000 !
b1001000 ,
b110 &
b110 )
#1359
b111111111111111111111111111111111 *
b11111111111111111111111110110111 !
b11111111111111111111111110110111 ,
b111 &
b111 )
#1379
b0 *
b1 !
b1 ,
b1000 &
b1000 )
#1399
b100 "
b100 +
b111111111111111111111111111111111 *
b11111111111111111111111110110111 !
b11111111111111111111111110110111 ,
b1001 &
b1001 )
#1419
b0 *
b0 !
b0 ,
b1010 &
b1010 )
#1439
b1011 &
b1011 )
#1459
b111111111111111111111111111111111 *
b10000000000000000000000000001000 !
b10000000000000000000000000001000 ,
b1100 &
b1100 )
#1479
b0 *
b1101 &
b1101 )
#1499
b10000000000000000000000001000000 !
b10000000000000000000000001000000 ,
b1110 &
b1110 )
#1519
b111111111111111111111111111111111 *
b1111111111111111111111110111111 !
b1111111111111111111111110111111 ,
b1111 &
b1111 )
#1622
b0 *
b11000000000000000000000000000000 !
b11000000000000000000000000000000 ,
b0 &
b0 )
b10111111111111111111111111111111 $
b10111111111111111111111111111111 (
b1 #
b1 '
#1642
b1 &
b1 )
#1662
b10 "
b10 +
b111111111111111111111111111111111 *
b1000000000000000000000000000010 !
b1000000000000000000000000000010 ,
b10 &
b10 )
#1682
b11 &
b11 )
#1702
b0 "
b0 +
b0 *
b1 !
b1 ,
b100 &
b100 )
#1722
b100 "
b100 +
b10111111111111111111111111111111 !
b10111111111111111111111111111111 ,
b101 &
b101 )
#1742
b10111111111111111111111111111110 !
b10111111111111111111111111111110 ,
b110 &
b110 )
#1762
b111111111111111111111111111111111 *
b1000000000000000000000000000001 !
b1000000000000000000000000000001 ,
b111 &
b111 )
#1782
b0 "
b0 +
b0 *
b1 !
b1 ,
b1000 &
b1000 )
#1802
b111111111111111111111111111111111 *
b1000000000000000000000000000001 !
b1000000000000000000000000000001 ,
b1001 &
b1001 )
#1822
b0 *
b0 !
b0 ,
b1010 &
b1010 )
#1842
b1011 &
b1011 )
#1862
b1100 &
b1100 )
#1882
b1 !
b1 ,
b1101 &
b1101 )
#1902
b10111111111111111111111111111111 !
b10111111111111111111111111111111 ,
b1110 &
b1110 )
#1922
b111111111111111111111111111111111 *
b1000000000000000000000000000000 !
b1000000000000000000000000000000 ,
b1111 &
b1111 )
#2025
b11 "
b11 +
b1 *
b1111111111111111111111111000100 !
b1111111111111111111111111000100 ,
b0 &
b0 )
b10111111111111111111111111000011 $
b10111111111111111111111111000011 (
b11000000000000000000000000000001 #
b11000000000000000000000000000001 '
#2045
b1 &
b1 )
#2065
b0 "
b0 +
b0 *
b111110 !
b111110 ,
b10 &
b10 )
#2085
b11 &
b11 )
#2105
b1 !
b1 ,
b100 &
b100 )
#2125
b100 "
b100 +
b11111111111111111111111111000011 !
b11111111111111111111111111000011 ,
b101 &
b101 )
#2145
b0 "
b0 +
b1111111111111111111111111000010 !
b1111111111111111111111111000010 ,
b110 &
b110 )
#2165
b111111111111111111111111111111111 *
b10000000000000000000000000111101 !
b10000000000000000000000000111101 ,
b111 &
b111 )
#2185
b0 *
b1 !
b1 ,
b1000 &
b1000 )
#2205
b100 "
b100 +
b111111111111111111111111111111111 *
b10000000000000000000000000111101 !
b10000000000000000000000000111101 ,
b1001 &
b1001 )
#2225
b0 *
b0 !
b0 ,
b1010 &
b1010 )
#2245
b1011 &
b1011 )
#2265
b111111111111111111111111111111111 *
b11111000000000000000000000000000 !
b11111000000000000000000000000000 ,
b1100 &
b1100 )
#2285
b0 *
b11000000000000000000000000000001 !
b11000000000000000000000000000001 ,
b1101 &
b1101 )
#2305
b10111111111111111111111111000011 !
b10111111111111111111111111000011 ,
b1110 &
b1110 )
#2325
b111111111111111111111111111111111 *
b1000000000000000000000000111100 !
b1000000000000000000000000111100 ,
b1111 &
b1111 )
