src/operand-handler.v

/***************************************************************
* Module: source_operand --> Source Operand2 Handler
****************************************************************
*
* Description:
* This module implements a source operand generator that selects and extends the appropriate operand based on the input opcode (IS) and immediate value (Imm). The module provides a 32-bit output (N) representing the selected and extended operand.
* 
* Inputs:
* - R [31:0]: 32-bit input register value
* - Imm [21:0]: 22-bit immediate value
* - IS [3:0]: 4-bit opcode representing the instruction type
* 
* Outputs:
* - N [31:0]: 32-bit output representing the selected and extended operand
* 
* Usage:
* 1. Instantiate the `source_operand` module in your design and provide the required inputs and outputs.
* 2. Connect the 32-bit input register value `R` to the desired source.
* 3. Assign the 22-bit immediate value `Imm` to the desired immediate value.
* 4. Set the 4-bit opcode `IS` to select the desired operation.
* 5. The output `N` will hold the selected and extended operand based on the opcode and immediate value.
* 
* Example:
* ```verilog
* module testbench;
*     reg [31:0] R;
*     reg [21:0] Imm;
*     reg [3:0] IS;
*     wire [31:0] N;
* 
*     source_operand source_operand_inst (
*         .R(R),
*         .Imm(Imm),
*         .IS(IS),
*         .N(N)
*     );
* 
*     initial begin
*         // Set input values
*         R = 32'hA5A5A5A5;
*         Imm = 22'h123456;
*         IS = 4'b0100; // Example opcode for sign extension operation
* 
*         // Wait some time for computation
*         #10;
* 
*         // Check output
*         $display("Result: %h", N);
*     end
* endmodule
* ```
***************************************************************/
module source_operand (
    input [31:0]       R,
    input [21:0]       Imm,
    input [3:0]        IS,
    output reg [31:0]  N
    );

    always @(*) begin
        case(IS)        
            4'b0000: N = {Imm, 10'b0}; // concatenate 10 0's to the right of Imm
            4'b0001: N = {Imm, 10'b0};
            4'b0010: N = {Imm, 10'b0};
            4'b0011: N = {Imm, 10'b0};
            4'b0100: begin
                if (Imm[21] == 1'b1) // if the sign bit is set
                    N = {10'b1111111111, Imm}; // sign extend with 1's
                else
                    N = {10'b0000000000, Imm}; // sign extend with 0's
            end
            4'b0101: begin
                if (Imm[21] == 1'b1) // if the sign bit is set
                    N = {10'b1111111111, Imm}; // sign extend with 1's
                else
                    N = {10'b0000000000, Imm}; // sign extend with 0's
            end
            4'b0110: begin
                if (Imm[21] == 1'b1) // if the sign bit is set
                    N = {10'b1111111111, Imm}; // sign extend with 1's
                else
                    N = {10'b0000000000, Imm}; // sign extend with 0's
            end
            4'b0111: begin
                if (Imm[21] == 1'b1) // if the sign bit is set
                    N = {10'b1111111111, Imm}; // sign extend with 1's
                else
                    N = {10'b0000000000, Imm}; // sign extend with 0's
            end
            4'b1000: N = R;
            4'b1001: begin
                if (Imm[21] == 1'b1) // if the sign bit is set
                    N = {22'b1111111111111111111111, Imm[12:0]}; // sign extend with 1's
                else
                    N = {22'b0000000000000000000000, Imm[12:0]}; // sign extend with 1's
            end
            4'b1010: N = {27'b0, R[4:0]};
            4'b1011: N = {27'b0, Imm[4:0]};
            4'b1100: N = R;        
            4'b1101: begin
                if (Imm[21] == 1'b1) // if the sign bit is set
                    N = {22'b1111111111111111111111, Imm[12:0]}; // sign extend with 1's
                else
                    N = {22'b0000000000000000000000, Imm[12:0]}; // sign extend with 1's
            end
            4'b1110: N = R;
            4'b1111: begin
                if (Imm[21] == 1'b1) // if the sign bit is set
                    N = {22'b1111111111111111111111, Imm[12:0]}; // sign extend with 1's
                else
                    N = {22'b0000000000000000000000, Imm[12:0]}; // sign extend with 1's
            end
        endcase
    end
endmodule

testers/operand-handler-tester.v
`timescale 1ns / 1ns
// `include "project/src/project-operand.v"
// `include "project-operand.v"

module operand_tb;

    reg [31:0] R;
    reg [21:0] Imm;
    reg [3:0] IS;
    wire [31:0] N;

    source_operand uut (
        .R(R),
        .Imm(Imm),
        .IS(IS),
        .N(N)
    );

    integer i;

    initial begin

        R = 32'b11100000000000000000000000000011;
        Imm = 22'b1000110001000100010011;

        
        
        IS = 4'b0000;
        repeat (15) #20 IS = IS + 4'b0001;

        Imm = 22'b1000110000000100010011;
        #3 $display(" ");
        
        
        IS = 4'b1000;
        repeat (7) #20 IS = IS + 4'b0001;
    end

    initial begin
        #3 $display("  IS |%17sR%16s|%10sImm%11s|%17sN%16s", "", "", "", "", "", "");
        #3 $display("-----|%s|%s|%s", "----------------------------------", "------------------------", "----------------------------------");
        #10 $monitor("%b | %b | %b | %b", IS, R, Imm, N);
    end

endmodule

gtk-wave-testers/operand-handler.vcd
$date
	Thu Jun  1 10:24:31 2023
$end
$version
	Icarus Verilog
$end
$timescale
	1ns
$end
$scope module operand_tb $end
$var wire 32 ! N [31:0] $end
$var reg 4 " IS [3:0] $end
$var reg 22 # Imm [21:0] $end
$var reg 32 $ R [31:0] $end
$scope module uut $end
$var wire 4 % IS [3:0] $end
$var wire 22 & Imm [21:0] $end
$var wire 32 ' R [31:0] $end
$var reg 32 ( N [31:0] $end
$upscope $end
$upscope $end
$enddefinitions $end
$comment Show the parameter values. $end
$dumpall
$end
#0
$dumpvars
b10001100010001000100110000000000 (
b11100000000000000000000000000011 '
b1000110001000100010011 &
b0 %
b11100000000000000000000000000011 $
b1000110001000100010011 #
b0 "
b10001100010001000100110000000000 !
$end
#20
b1 "
b1 %
#40
b10 "
b10 %
#60
b11 "
b11 %
#80
b11111111111000110001000100010011 !
b11111111111000110001000100010011 (
b100 "
b100 %
#100
b101 "
b101 %
#120
b110 "
b110 %
#140
b111 "
b111 %
#160
b11100000000000000000000000000011 !
b11100000000000000000000000000011 (
b1000 "
b1000 %
#180
b11111111111111111111000100010011 !
b11111111111111111111000100010011 (
b1001 "
b1001 %
#200
b11 !
b11 (
b1010 "
b1010 %
#220
b10011 !
b10011 (
b1011 "
b1011 %
#240
b11100000000000000000000000000011 !
b11100000000000000000000000000011 (
b1100 "
b1100 %
#260
b11111111111111111111000100010011 !
b11111111111111111111000100010011 (
b1101 "
b1101 %
#280
b11100000000000000000000000000011 !
b11100000000000000000000000000011 (
b1110 "
b1110 %
#300
b11111111111111111110000100010011 !
b11111111111111111110000100010011 (
b1000110000000100010011 #
b1000110000000100010011 &
b1111 "
b1111 %
#303
b11100000000000000000000000000011 !
b11100000000000000000000000000011 (
b1000 "
b1000 %
#323
b11111111111111111110000100010011 !
b11111111111111111110000100010011 (
b1001 "
b1001 %
#343
b11 !
b11 (
b1010 "
b1010 %
#363
b10011 !
b10011 (
b1011 "
b1011 %
#383
b11100000000000000000000000000011 !
b11100000000000000000000000000011 (
b1100 "
b1100 %
#403
b11111111111111111110000100010011 !
b11111111111111111110000100010011 (
b1101 "
b1101 %
#423
b11100000000000000000000000000011 !
b11100000000000000000000000000011 (
b1110 "
b1110 %
#443
b11111111111111111110000100010011 !
b11111111111111111110000100010011 (
b1111 "
b1111 %
